format_dedent/__init__.py
format_dedent/__main__.py
format_dedent/add_dedent.py
format_dedent/ast_helpers.py
format_dedent/cli.py
format_dedent/formatter.py
format_dedent-0.1.1.dist-info/METADATA
format_dedent-0.1.1.dist-info/WHEEL
format_dedent-0.1.1.dist-info/entry_points.txt
format_dedent-0.1.1.dist-info/top_level.txt
format_dedent-0.1.1.dist-info/RECORD
