Metadata-Version: 2.4
Name: format-dedent
Version: 0.1.1
Summary: Format only the literal string arguments of textwrap.dedent() calls
License-Expression: MIT
Keywords: formatter,textwrap,dedent,pre-commit
Classifier: Development Status :: 4 - Beta
Classifier: Intended Audience :: Developers
Classifier: Programming Language :: Python :: 3
Classifier: Programming Language :: Python :: 3.8
Classifier: Programming Language :: Python :: 3.9
Classifier: Programming Language :: Python :: 3.10
Classifier: Programming Language :: Python :: 3.11
Classifier: Programming Language :: Python :: 3.12
Classifier: Topic :: Software Development :: Quality Assurance
Requires-Python: >=3.8
Provides-Extra: dev
Requires-Dist: pytest>=7.0; extra == "dev"
Requires-Dist: inline-snapshot[black]>=0.13.0; extra == "dev"
Requires-Dist: pre-commit>=3.0.0; extra == "dev"
